ds4ml/__init__.py
ds4ml/__version__.py
ds4ml/attribute.py
ds4ml/dataset.py
ds4ml/evaluator.py
ds4ml/metrics.py
ds4ml/synthesizer.py
ds4ml/utils.py
ds4ml/command/__init__.py
ds4ml/command/evaluate.py
ds4ml/command/pattern.py
ds4ml/command/synthesize.py
ds4ml/template/report.html
ds4ml-0.3.6.dist-info/LICENSE
ds4ml-0.3.6.dist-info/METADATA
ds4ml-0.3.6.dist-info/WHEEL
ds4ml-0.3.6.dist-info/entry_points.txt
ds4ml-0.3.6.dist-info/top_level.txt
ds4ml-0.3.6.dist-info/RECORD
