Metadata-Version: 2.1
Name: ds4ml
Version: 0.3.6
Summary: A Python library for data synthesis and evaluation
Home-page: https://github.com/SAP/data-synthesis-for-machine-learning
Maintainer: Yan Zhao
Maintainer-email: yan.zhao01@sap.com
Project-URL: Bug Tracker, https://github.com/SAP/data-synthesis-for-machine-learning/issues
Project-URL: Documentation, https://github.com/SAP/data-synthesis-for-machine-learning
Project-URL: Source Code, https://github.com/SAP/data-synthesis-for-machine-learning
License-File: LICENSE
Requires-Dist: numpy >=1.14.3
Requires-Dist: matplotlib >=2.2.2
Requires-Dist: mako >=1.2.2
Requires-Dist: pandas >=0.24.2
Requires-Dist: scikit-learn >=0.20.2
Requires-Dist: python-dateutil >=2.7.3
